odoo8_addon_product_categ_image-8.0.0.1.1-nspkg.pth
odoo_addons/product_categ_image/README.rst
odoo_addons/product_categ_image/__init__.py
odoo_addons/product_categ_image/__openerp__.py
odoo_addons/product_categ_image/i18n/product_categ_image.pot
odoo_addons/product_categ_image/models/__init__.py
odoo_addons/product_categ_image/models/product_category.py
odoo_addons/product_categ_image/static/description/icon.png
odoo_addons/product_categ_image/views/product_view.xml
odoo8_addon_product_categ_image-8.0.0.1.1.dist-info/METADATA
odoo8_addon_product_categ_image-8.0.0.1.1.dist-info/WHEEL
odoo8_addon_product_categ_image-8.0.0.1.1.dist-info/namespace_packages.txt
odoo8_addon_product_categ_image-8.0.0.1.1.dist-info/top_level.txt
odoo8_addon_product_categ_image-8.0.0.1.1.dist-info/RECORD
